aio_daemon/__init__.py
aio_daemon/daemon.py
aio_daemon/env.py
aio_daemon/json.py
aio_daemon/logging.py
aio_daemon-1.0.dist-info/LICENSE
aio_daemon-1.0.dist-info/METADATA
aio_daemon-1.0.dist-info/WHEEL
aio_daemon-1.0.dist-info/top_level.txt
aio_daemon-1.0.dist-info/RECORD
