Metadata-Version: 2.1
Name: aio_daemon
Version: 1.0
Summary: Helper module for running async daemons.
Home-page: https://github.com/Trogious/aio-daemon
Author: Trog
Author-email: trog@swmud.net
Classifier: Programming Language :: Python :: 3.7
Classifier: Programming Language :: Python :: 3.8
Classifier: Programming Language :: Python :: 3.9
Classifier: License :: OSI Approved :: MIT License
Classifier: Operating System :: OS Independent
Classifier: Topic :: Software Development :: Libraries :: Python Modules
Classifier: Development Status :: 4 - Beta
Requires-Python: >=3.7
License-File: LICENSE
